Metadata-Version: 1.0
Name: core-json-app
Version: 1.0.0a12
Summary: JSON support for the curator core project
Home-page: https://github.com/usnistgov/core_json_app
Author: NIST IT Lab
Author-email: itl_inquiries@nist.gov
License: UNKNOWN
Platform: UNKNOWN
